src/dj_vditor/__init__.py
src/dj_vditor/apps.py
src/dj_vditor/configs.py
src/dj_vditor/fields.py
src/dj_vditor/oss.py
src/dj_vditor/views.py
src/dj_vditor/widgets.py
dj_vditor-0.1.6.dist-info/LICENSE
dj_vditor-0.1.6.dist-info/METADATA
dj_vditor-0.1.6.dist-info/WHEEL
dj_vditor-0.1.6.dist-info/top_level.txt
dj_vditor-0.1.6.dist-info/RECORD
