Metadata-Version: 2.2
Name: dj-vditor
Version: 0.1.6
Summary: Django vditor integration
Home-page: https://github.com/ren000thomas/django-vditor
Author: Ren Thomas
Author-email: ren000thomas@gmail.com
License: MIT
Classifier: Framework :: Django
Classifier: Programming Language :: Python :: 3
Classifier: License :: OSI Approved :: MIT License
Requires-Python: >=3.6
License-File: LICENSE
Requires-Dist: Django>=4.0
Requires-Dist: oss2>=2.15.0
